LICENSE
MANIFEST.in
README.md
setup.py
drfdocs.egg-info/PKG-INFO
drfdocs.egg-info/SOURCES.txt
drfdocs.egg-info/dependency_links.txt
drfdocs.egg-info/top_level.txt
rest_framework_docs/__init__.py
rest_framework_docs/api_docs.py
rest_framework_docs/api_endpoint.py
rest_framework_docs/settings.py
rest_framework_docs/urls.py
rest_framework_docs/views.py
rest_framework_docs/static/rest_framework_docs/css/style.css
rest_framework_docs/static/rest_framework_docs/fonts/FontAwesome.otf
rest_framework_docs/static/rest_framework_docs/fonts/fontawesome-webfont.eot
rest_framework_docs/static/rest_framework_docs/fonts/fontawesome-webfont.svg
rest_framework_docs/static/rest_framework_docs/fonts/fontawesome-webfont.ttf
rest_framework_docs/static/rest_framework_docs/fonts/fontawesome-webfont.woff
rest_framework_docs/static/rest_framework_docs/fonts/fontawesome-webfont.woff2
rest_framework_docs/static/rest_framework_docs/fonts/glyphicons-halflings-regular.eot
rest_framework_docs/static/rest_framework_docs/fonts/glyphicons-halflings-regular.svg
rest_framework_docs/static/rest_framework_docs/fonts/glyphicons-halflings-regular.ttf
rest_framework_docs/static/rest_framework_docs/fonts/glyphicons-halflings-regular.woff
rest_framework_docs/static/rest_framework_docs/fonts/glyphicons-halflings-regular.woff2
rest_framework_docs/static/rest_framework_docs/js/dist.min.js
rest_framework_docs/static/rest_framework_docs/less/style.less
rest_framework_docs/templates/rest_framework_docs/base.html
rest_framework_docs/templates/rest_framework_docs/docs.html
rest_framework_docs/templates/rest_framework_docs/home.html
site/__init__.py
site/template/__init__.py
tests/__init__.py
tests/models.py
tests/serializers.py
tests/settings.py
tests/tests.py
tests/urls.py
tests/views.py